docTagger/TfIdf_Vectorizer.pk
docTagger/__init__.py
docTagger/cnb.pk
docTagger/docTagger.py
docTagger-0.21.dist-info/METADATA
docTagger-0.21.dist-info/WHEEL
docTagger-0.21.dist-info/top_level.txt
docTagger-0.21.dist-info/RECORD
